Metadata-Version: 2.4
Name: mcp-feedback-collector-beta
Version: 3.2.1
Summary: A modern MCP server with dual interface (GUI + Web) for AI feedback collection and chat
Project-URL: Homepage, https://github.com/sanshao85/mcp-feedback-collector
Project-URL: Repository, https://github.com/sanshao85/mcp-feedback-collector
Project-URL: Documentation, https://github.com/sanshao85/mcp-feedback-collector#readme
Project-URL: Bug Tracker, https://github.com/sanshao85/mcp-feedback-collector/issues
Author-email: MCP Feedback Collector <feedback@example.com>
License: MIT
License-File: LICENSE
Keywords: ai-assistant,ai-chat,cherry-studio,claude,dual-interface,feedback,flask,gui,image-picker,interactive,mcp,model-context-protocol,socketio,web
Classifier: Development Status :: 4 - Beta
Classifier: Environment :: Console
Classifier: Environment :: MacOS X
Classifier: Environment :: Win32 (MS Windows)
Classifier: Environment :: X11 Applications
Classifier: Intended Audience :: Developers
Classifier: Intended Audience :: End Users/Desktop
Classifier: License :: OSI Approved :: MIT License
Classifier: Operating System :: OS Independent
Classifier: Programming Language :: Python :: 3
Classifier: Programming Language :: Python :: 3.8
Classifier: Programming Language :: Python :: 3.9
Classifier: Programming Language :: Python :: 3.10
Classifier: Programming Language :: Python :: 3.11
Classifier: Programming Language :: Python :: 3.12
Classifier: Topic :: Communications
Classifier: Topic :: Internet
Classifier: Topic :: Scientific/Engineering :: Artificial Intelligence
Classifier: Topic :: Software Development :: Libraries :: Python Modules
Classifier: Topic :: System :: Networking
Classifier: Topic :: Utilities
Requires-Python: >=3.8
Requires-Dist: flask-socketio>=5.0.0
Requires-Dist: flask>=2.0.0
Requires-Dist: mcp>=1.0.0
Requires-Dist: pillow>=9.0.0
Requires-Dist: psutil>=5.8.0
Requires-Dist: requests>=2.25.0
Provides-Extra: dev
Requires-Dist: black; extra == 'dev'
Requires-Dist: isort; extra == 'dev'
Requires-Dist: mypy; extra == 'dev'
Requires-Dist: pytest>=6.0; extra == 'dev'
Provides-Extra: gui
Requires-Dist: pyqt6>=6.0.0; extra == 'gui'
